{
    "region": "City",
    "name": "",
    "type": "Polygon",
    "coordinates": [
        [
            [
                -4.49977,
                30.81603
            ],
            [
                -4.4932,
                30.82035
            ],
            [
                -4.48843,
                30.82145
            ],
            [
                -4.48463,
                30.82125
            ],
            [
                -4.48704,
                30.81868
            ],
            [
                -4.49576,
                30.81522
            ],
            [
                -4.49676793569043,
                30.81302104760685
            ],
            [
                -4.49883744382123,
                30.81353842463955
            ]
        ]
    ],
    "secret": false
}